app_manager/__init__.py
app_manager/main.py
app_manager-0.0.0.2.dist-info/LICENSE
app_manager-0.0.0.2.dist-info/METADATA
app_manager-0.0.0.2.dist-info/WHEEL
app_manager-0.0.0.2.dist-info/top_level.txt
app_manager-0.0.0.2.dist-info/RECORD
