Metadata-Version: 2.1
Name: app-manager
Version: 0.0.0.2
Summary: Runs Python application in a fault-tolerant environment, continually rebooting after unexpected exceptions
Home-page: https://github.com/jmsimons/app_manager
Author: Jared Simons
Author-email: jmsimons@lcmail.lcsc.edu
License: UNKNOWN
Platform: UNKNOWN
